MazeSolvingAlgos.cp39-win_amd64.pyd
MazeSolvingAlgos-1.4.dist-info/METADATA
MazeSolvingAlgos-1.4.dist-info/WHEEL
MazeSolvingAlgos-1.4.dist-info/top_level.txt
MazeSolvingAlgos-1.4.dist-info/RECORD
