Metadata-Version: 2.1
Name: MazeSolvingAlgos
Version: 1.4
Summary: Python module written in C++ for generating and solving rectangular Mazes with Graph Traversal Algorithms.
Author-email: Mahmoud Hussien Mohamed <MahmoudHussienMohamed.mhm@gmail.com>
Project-URL: Homepage, https://github.com/MahmoudHussienMohamed/MazeSolvingAlgos
Project-URL: repository, https://github.com/MahmoudHussienMohamed/MazeSolvingAlgos
Project-URL: Bug Tracker, https://github.com/MahmoudHussienMohamed/MazeSolvingAlgos/issues
Project-URL: documentation, https://github.com/MahmoudHussienMohamed/MazeSolvingAlgos/wiki/Documentation
Classifier: Programming Language :: C++
Classifier: License :: OSI Approved :: GNU General Public License v3 (GPLv3)
Classifier: Operating System :: Microsoft :: Windows
